.hgignore
.hgtags
Dockerfile
LICENSE.txt
build.sh
run.sh
setup.py
test.sh
modjango/__init__.py
modjango/test.py
modjango.egg-info/PKG-INFO
modjango.egg-info/SOURCES.txt
modjango.egg-info/dependency_links.txt
modjango.egg-info/requires.txt
modjango.egg-info/top_level.txt