Metadata-Version: 1.1
Name: modjango
Version: 1.2.1
Summary: mongoengine integration for django
Home-page: UNKNOWN
Author: Philip Zerull
Author-email: przerull@gmail.com
License: UNKNOWN
Platform: UNKNOWN
Provides: modjango
